Workbook

Sheet Assumptions
A1: Cost-Benefit Model — Assumptions
A2: Yellow cells are editable inputs. Every other tab calculates from these cells — change a value here and the whole model recalculates.
A3: Category | B3: Assumption | C3: Value | D3: Notes / Source
A4: Scope | B4: Number of stores in scope | C4: 12 | D4: Illustrative pilot rollout across store footprint (portfolio mock scenario)
A5: Scope | B5: Weeks per year | C5: 52 | D5: Standard calendar
A6: Labor Rates | B6: Store manager hourly rate | C6: 28 | D6: Illustrative fully-loaded hourly rate (portfolio mock scenario)
A7: Labor Rates | B7: Business/Data analyst hourly rate | C7: 45 | D7: Illustrative fully-loaded hourly rate (portfolio mock scenario)
A8: Current State (As-Is) | B8: Manual reporting hours/week per store — current | C8: 3 | D8: Time store manager spends compiling sales data manually today
A9: Current State (As-Is) | B9: Ad hoc analysis requests to BA per month — current | C9: 8 | D9: Requests routed to analyst because no self-serve dashboard exists
A10: Current State (As-Is) | B10: Avg hours per ad hoc request | C10: 4
A11: Future State (To-Be) | B11: Manual reporting hours/week per store — future | C11: 0.5 | D11: Time to review self-serve dashboard vs. compile a manual report
A12: Future State (To-Be) | B12: Reduction in ad hoc analysis requests | C12: 0.7 | D12: Reduction once dashboard answers recurring questions directly
A13: Revenue | B13: Average monthly revenue per store | C13: 45000 | D13: Illustrative — see coffeeOrdersProject.xlsx for underlying sales data
A14: Revenue | B14: Revenue uplift from staffing optimization | C14: 0.0015 | D14: % of revenue — matching staffing to peak order-time data (conservative operational-efficiency estimate)
A15: Revenue | B15: Revenue recovered from reduced data-quality leakage | C15: 0.001 | D15: % of revenue — fewer duplicate/void/miskeyed orders (BRD requirements FR-2, FR-7)
A16: Recurring Cost Drivers | B16: Number of licensed dashboard users | C16: 15 | D16: Store managers + regional ops + finance reviewers
A17: Recurring Cost Drivers | B17: Monthly BI licensing cost per user | C17: 10 | D17: Illustrative Power BI Pro per-user list price
A18: Recurring Cost Drivers | B18: Annual dashboard maintenance hours | C18: 30 | D18: BA hours/year to maintain dashboard and data pipeline as needs evolve
A19: Recurring Cost Drivers | B19: Data quality monitoring hours per quarter | C19: 10 | D19: BA hours/quarter reviewing data-quality exception logs (BRD FR-7)
A20: Financial | B20: Discount rate (annual, cost of capital) | C20: 0.08 | D20: Illustrative WACC assumption
A21: Financial | B21: Analysis horizon | C21: 3 | D21: years
A22: Financial | B22: Contingency on one-time implementation costs | C22: 0.1 | D22: Buffer applied to implementation estimate

Sheet One-Time Costs
A1: Implementation Cost — One-Time (Year 0)
A3: Item | B3: Quantity | C3: Unit Cost ($/hr) | D3: Total Cost
A4: Requirements & business analysis (BRD, CBA) | B4: 60 | C4: =Assumptions!$C$7 | D4: =B4*C4
A5: Dashboard build (Power BI development) | B5: 150 | C5: =Assumptions!$C$7 | D5: =B5*C5
A6: Data pipeline / cleaning automation setup | B6: 120 | C6: =Assumptions!$C$7 | D6: =B6*C6
A7: Store manager training (all stores x 2 hrs) | B7: =Assumptions!$C$4*2 | C7: =Assumptions!$C$6 | D7: =B7*C7
A9: Subtotal | D9: =SUM(D4:D7)
A10: Contingency | B10: =Assumptions!$C$22 | D10: =D9*B10
A11: Total One-Time Cost | D11: =D9+D10

Sheet Recurring Costs
A1: Recurring Cost — Annual (Years 1-3)
A3: Item | B3: Quantity | C3: Unit Cost | D3: Annual Cost
A4: BI dashboard licensing | B4: =Assumptions!$C$16 | C4: =Assumptions!$C$17*12 | D4: =B4*C4
A5: Dashboard maintenance | B5: =Assumptions!$C$18 | C5: =Assumptions!$C$7 | D5: =B5*C5
A6: Data quality monitoring (4 quarters/year) | B6: =Assumptions!$C$19*4 | C6: =Assumptions!$C$7 | D6: =B6*C6
A8: Total Annual Recurring Cost | D8: =SUM(D4:D6)

Sheet Benefits
A1: Quantified Benefits — Annual (Years 1-3)
A3: Item | B3: Basis | D3: Annual Benefit
A4: Store manager reporting time savings | B4: (current hrs/wk − future hrs/wk) × weeks/yr × stores × manager rate | D4: =(Assumptions!$C$8-Assumptions!$C$11)*Assumptions!$C$5*Assumptions!$C$4*Assumptions!$C$6
A5: BA time savings from reduced ad hoc requests | B5: requests/mo × 12 × hrs/request × reduction% × analyst rate | D5: =Assumptions!$C$9*12*Assumptions!$C$10*Assumptions!$C$12*Assumptions!$C$7
A6: Revenue uplift — staffing optimization | B6: stores × monthly revenue × 12 × uplift% | D6: =Assumptions!$C$4*Assumptions!$C$13*12*Assumptions!$C$14
A7: Revenue recovered — data quality improvement | B7: stores × monthly revenue × 12 × recovery% | D7: =Assumptions!$C$4*Assumptions!$C$13*12*Assumptions!$C$15
A9: Total Annual Benefit | D9: =SUM(D4:D7)

Sheet Summary & ROI
A1: Cost-Benefit Summary — Order Management System Enhancement
A3: Year | B3: Net Cash Flow | C3: Discount Factor | D3: Present Value
A4: 0 | B4: =-'One-Time Costs'!$D$11 | C4: =1/(1+Assumptions!$C$20)^A4 | D4: =B4*C4
A5: 1 | B5: =Benefits!$D$9-'Recurring Costs'!$D$8 | C5: =1/(1+Assumptions!$C$20)^A5 | D5: =B5*C5
A6: 2 | B6: =Benefits!$D$9-'Recurring Costs'!$D$8 | C6: =1/(1+Assumptions!$C$20)^A6 | D6: =B6*C6
A7: 3 | B7: =Benefits!$D$9-'Recurring Costs'!$D$8 | C7: =1/(1+Assumptions!$C$20)^A7 | D7: =B7*C7
A9: Net Present Value (NPV) | D9: =SUM(D4:D7)
A11: Payback Period (years, undiscounted) | D11: =-B4/B5
A12: Total 3-Year Benefits (undiscounted) | D12: =Benefits!$D$9*Assumptions!$C$21
A13: Total 3-Year Costs (one-time + recurring, undiscounted) | D13: ='One-Time Costs'!$D$11+'Recurring Costs'!$D$8*Assumptions!$C$21
A14: 3-Year ROI | D14: =(D12-D13)/D13
A16: Note: Years 1-3 assume steady-state annual benefit/recurring cost (no ramp-up). All figures are illustrative planning assumptions for this portfolio scenario, not audited financials.
